backoff/__init__.py
backoff/common/__init__.py
backoff/common/backoff_config.py
backoff/common/constants.py
backoff/common/error_code.py
backoff/common/result_entity.py
backoff/common/task_entity.py
backoff/conf/logging.config.yaml
backoff/core/__init__.py
backoff/core/backoff_worker.py
backoff/core/embedding.py
backoff/core/task_repository.py
backoff/models/__init__.py
backoff/models/backoff_threadpool.py
backoff/models/redis_client.py
backoff/models/redis_lock.py
backoff/repository/__init__.py
backoff/repository/redis_adapter.py
backoff/repository/storage_adapter.py
backoff/scheduler/__init__.py
backoff/scheduler/backoff_scheduler.py
backoff/scheduler/biz_task_scheduler.py
backoff/utils/__init__.py
backoff/utils/date_utils.py
backoff/utils/gpu_utils.py
backoff/utils/logging_utils.py
backoff/utils/serialize_data_utils.py
maas_backoff_scheduler-1.1.9.dist-info/LICENSE
maas_backoff_scheduler-1.1.9.dist-info/METADATA
maas_backoff_scheduler-1.1.9.dist-info/WHEEL
maas_backoff_scheduler-1.1.9.dist-info/top_level.txt
maas_backoff_scheduler-1.1.9.dist-info/RECORD
