Metadata-Version: 2.1
Name: maas-backoff-scheduler
Version: 1.1.9
Summary: 基于Redis的任务退避重试框架，支持多种退避策略
Home-page: https://github.com/xiaofucoding/maas-backoff-scheduler.git/
Author: xinzf
Author-email: 515361725@qq.com
License: MIT
Project-URL: Source, https://github.com/yourusername/task-backoff-scheduler
Project-URL: Documentation, https://github.com/yourusername/task-backoff-scheduler#readme
Project-URL: Bug Reports, https://github.com/yourusername/task-backoff-scheduler/issues
Keywords: task retry backoff redis queue
Platform: UNKNOWN
Classifier: Development Status :: 4 - Beta
Classifier: Intended Audience :: Developers
Classifier: License :: OSI Approved :: MIT License
Classifier: Operating System :: OS Independent
Classifier: Programming Language :: Python :: 3
Classifier: Programming Language :: Python :: 3.7
Classifier: Programming Language :: Python :: 3.8
Classifier: Programming Language :: Python :: 3.9
Classifier: Programming Language :: Python :: 3.10
Classifier: Programming Language :: Python :: 3.11
Requires-Python: >=3.7
Requires-Dist: redis (>=4.0.0)
Requires-Dist: PyYAML (>=6.0)
Requires-Dist: dataclasses (>=0.6) ; python_version < "3.7"
Provides-Extra: dev
Requires-Dist: pytest (>=6.0.0) ; extra == 'dev'
Requires-Dist: pytest-cov (>=2.0.0) ; extra == 'dev'
Requires-Dist: black (>=21.0.0) ; extra == 'dev'
Requires-Dist: flake8 (>=3.8.0) ; extra == 'dev'
Requires-Dist: mypy (>=0.800) ; extra == 'dev'
